[
  {
    "name": { "str": "XL mask of disappearance", "str_pl": "XL masks of disappearance" },
    "copy-from": "mmask_disappearance",
    "type": "TOOL_ARMOR",
    "proportional": { "weight": 1.2, "volume": 1.2, "storage": 1.2, "encumbrance": 1.2 },
    "extend": { "flags": [ "OVERSIZE" ] },
    "id": "mmask_disappearance_xl",
    "description": "A mask with no facial features at all, just eye and mouth holes, upon activation it makes everything ignore your presence for a while.  This can be worn regardless of your state of mutation"
  },
  {
    "name": { "str": "XL mask of perfect vision", "str_pl": "XL masks of perfect vision" },
    "copy-from": "mmask_vision",
    "type": "TOOL_ARMOR",
    "proportional": { "weight": 1.2, "volume": 1.2, "storage": 1.2, "encumbrance": 1.2 },
    "extend": { "flags": [ "OVERSIZE" ] },
    "id": "mmask_vision_xl",
    "description": "A decidedly steampunk-looking half mask that covers the eye area of the face, it has large lenses that correct and greatly enhance the vision of the wearer.  This can be worn regardless of your state of mutation"
  }
]
